{"title":"关于我","uid":"6106358612db23cbb4b9c28644b3853a","text":"欢迎来到依水何安的博客 本人是一个险些00后的90后，研二在读，目前就读于东南大学，信息与通信工程专业。菜鸡一枚，本站主要是记录一些技术分享以及平时的碎碎念，希望你能够喜欢~ 如果你也喜欢这些，那我们一定很合得来： 抽象文化，包括但不限于各种狠活，阿牛小卖部以及东百往事(纯路人)...","date":"2022-09-01T14:59:53.000Z","updated":"2022-09-18T07:19:30.398Z","comments":true,"path":"api/pages/about/index.json","covers":[],"excerpt":"","content":"<h1 id=\"欢迎来到依水何安的博客\"><a href=\"#欢迎来到依水何安的博客\" class=\"headerlink\" title=\"欢迎来到依水何安的博客\"></a>欢迎来到依水何安的博客</h1><p><img src=\"https://cdn.staticaly.com/gh/jankin12138/IMG@main/img/sky3_4k.19f3y3065l28.webp\" alt=\"sky3_4k\"></p>\n<p>本人是一个险些00后的90后，研二在读，目前就读于东南大学，信息与通信工程专业。菜鸡一枚，本站主要是记录一些<strong>技术分享</strong>以及<strong>平时的碎碎念</strong>，希望你能够喜欢~</p>\n<h2 id=\"如果你也喜欢这些，那我们一定很合得来：\"><a href=\"#如果你也喜欢这些，那我们一定很合得来：\" class=\"headerlink\" title=\"如果你也喜欢这些，那我们一定很合得来：\"></a>如果你也喜欢这些，那我们一定很合得来：</h2><ul>\n<li><strong>抽象文化</strong>，包括但不限于各种狠活，阿牛小卖部以及东百往事(纯路人)</li>\n<li><strong>狠狠刷题</strong>，力扣刷题是一件漫长但是又很容易坚持的有趣的事情</li>\n<li><strong>分布式系统以及项目合作开发</strong>，前些日子和小伙伴一起开发真的非常有趣</li>\n</ul>\n<h2 id=\"联系我\"><a href=\"#联系我\" class=\"headerlink\" title=\"联系我\"></a>联系我</h2><p>感觉不是啥大忙人直接站内留言就好辣，哈哈哈</p>\n","count_time":{"symbolsCount":229,"symbolsTime":"1 mins."},"toc":"<ol class=\"toc\"><li class=\"toc-item toc-level-1\"><a class=\"toc-link\" href=\"#%E6%AC%A2%E8%BF%8E%E6%9D%A5%E5%88%B0%E4%BE%9D%E6%B0%B4%E4%BD%95%E5%AE%89%E7%9A%84%E5%8D%9A%E5%AE%A2\"><span class=\"toc-text\">欢迎来到依水何安的博客</span></a><ol class=\"toc-child\"><li class=\"toc-item toc-level-2\"><a class=\"toc-link\" href=\"#%E5%A6%82%E6%9E%9C%E4%BD%A0%E4%B9%9F%E5%96%9C%E6%AC%A2%E8%BF%99%E4%BA%9B%EF%BC%8C%E9%82%A3%E6%88%91%E4%BB%AC%E4%B8%80%E5%AE%9A%E5%BE%88%E5%90%88%E5%BE%97%E6%9D%A5%EF%BC%9A\"><span class=\"toc-text\">如果你也喜欢这些，那我们一定很合得来：</span></a></li><li class=\"toc-item toc-level-2\"><a class=\"toc-link\" href=\"#%E8%81%94%E7%B3%BB%E6%88%91\"><span class=\"toc-text\">联系我</span></a></li></ol></li></ol>"}